tyconf/__init__.py
tyconf/core.py
tyconf/validators.py
tyconf-1.1.0.dist-info/licenses/LICENSE
tyconf-1.1.0.dist-info/METADATA
tyconf-1.1.0.dist-info/WHEEL
tyconf-1.1.0.dist-info/top_level.txt
tyconf-1.1.0.dist-info/RECORD
