Metadata-Version: 2.4
Name: tyconf
Version: 1.1.0
Summary: TyConf - Type-safe Configuration Management for Python with Value Validation
Author-email: barabasz <tyconf@anba.ovh>
License-Expression: MIT
Project-URL: Homepage, https://github.com/barabasz/tyconf
Project-URL: Documentation, https://github.com/barabasz/tyconf/blob/main/docs/user_guide.md
Project-URL: Repository, https://github.com/barabasz/tyconf
Project-URL: Issues, https://github.com/barabasz/tyconf/issues
Project-URL: Changelog, https://github.com/barabasz/tyconf/blob/main/CHANGELOG.md
Keywords: configuration,config,settings,typed,validation,type-safe,validators
Classifier: Development Status :: 5 - Production/Stable
Classifier: Intended Audience :: Developers
Classifier: Operating System :: OS Independent
Classifier: Programming Language :: Python :: 3
Classifier: Programming Language :: Python :: 3.10
Classifier: Programming Language :: Python :: 3.11
Classifier: Programming Language :: Python :: 3.12
Classifier: Programming Language :: Python :: 3.13
Classifier: Topic :: Software Development :: Libraries :: Python Modules
Classifier: Topic :: Utilities
Classifier: Typing :: Typed
Requires-Python: >=3.10
License-File: LICENSE
Provides-Extra: dev
Requires-Dist: pytest>=7.0.0; extra == "dev"
Requires-Dist: pytest-cov>=4.0.0; extra == "dev"
Requires-Dist: black>=23.0.0; extra == "dev"
Requires-Dist: flake8>=6.0.0; extra == "dev"
Requires-Dist: mypy>=1.0.0; extra == "dev"
Dynamic: license-file
